browser_detection/__init__.py
browser_detection/example.py
browser_detection/frontend/build/asset-manifest.json
browser_detection/frontend/build/bootstrap.min.css
browser_detection/frontend/build/bootstrap.min.css.map
browser_detection/frontend/build/index.html
browser_detection/frontend/build/static/js/main.1f5d17bf.js
browser_detection/frontend/build/static/js/main.1f5d17bf.js.LICENSE.txt
browser_detection/frontend/build/static/js/main.1f5d17bf.js.map
streamlit_browser_engine-0.0.3.dist-info/LICENSE
streamlit_browser_engine-0.0.3.dist-info/METADATA
streamlit_browser_engine-0.0.3.dist-info/WHEEL
streamlit_browser_engine-0.0.3.dist-info/top_level.txt
streamlit_browser_engine-0.0.3.dist-info/RECORD
